docplex_extensions/__init__.py
docplex_extensions/_dict_mixins.py
docplex_extensions/_index_sets.py
docplex_extensions/_model_funcs.py
docplex_extensions/_pandas_accessors.py
docplex_extensions/_param_dicts.py
docplex_extensions/_tuning_funcs.py
docplex_extensions/_var_dicts.py
docplex_extensions/_var_funcs.py
docplex_extensions/py.typed
docplex_extensions-1.3.1.dist-info/licenses/LICENSE
docplex_extensions-1.3.1.dist-info/licenses/NOTICE
docplex_extensions-1.3.1.dist-info/METADATA
docplex_extensions-1.3.1.dist-info/WHEEL
docplex_extensions-1.3.1.dist-info/top_level.txt
docplex_extensions-1.3.1.dist-info/RECORD
