Metadata-Version: 2.4
Name: docplex-extensions
Version: 1.3.1
Summary: Custom data structures and user-friendly functions for modeling with DOcplex
Author-email: Samarth Mistry <samarth.mistry@gmail.com>
License:                                  Apache License
Project-URL: Documentation, https://docplex-extensions.readthedocs.io/en/stable
Project-URL: Source code, https://github.com/samarthmistry/docplex-extensions
Project-URL: Changelog, https://github.com/samarthmistry/docplex-extensions/releases
Classifier: License :: OSI Approved :: Apache Software License
Classifier: Development Status :: 5 - Production/Stable
Classifier: Intended Audience :: Developers
Classifier: Intended Audience :: Information Technology
Classifier: Intended Audience :: Science/Research
Classifier: Operating System :: OS Independent
Classifier: Programming Language :: Python
Classifier: Programming Language :: Python :: 3.10
Classifier: Programming Language :: Python :: 3.11
Classifier: Programming Language :: Python :: 3.12
Classifier: Programming Language :: Python :: 3.13
Classifier: Typing :: Typed
Requires-Python: >=3.10
License-File: LICENSE
License-File: NOTICE
Requires-Dist: typing_extensions>=4.10.0
Requires-Dist: docplex>=2.25.236
Provides-Extra: cplex-runtime
Requires-Dist: cplex>=20.1.0.4; extra == "cplex-runtime"
Provides-Extra: tests
Requires-Dist: pytest>=8.1.1; extra == "tests"
Requires-Dist: coverage>=7.4.4; extra == "tests"
Requires-Dist: pytest-cov>=4.1.0; extra == "tests"
Requires-Dist: pytest-randomly>=3.15.0; extra == "tests"
Requires-Dist: mypy[faster-cache]>=1.13.0; extra == "tests"
Requires-Dist: pandas>=1.5.0; extra == "tests"
Requires-Dist: pandas-stubs>=1.5.0; extra == "tests"
Provides-Extra: docs
Requires-Dist: Sphinx==8.0.2; extra == "docs"
Requires-Dist: sphinx-autosummary-accessors==2023.4.0; extra == "docs"
Requires-Dist: numpydoc==1.8.0; extra == "docs"
Requires-Dist: ansys-sphinx-theme==1.0.3; extra == "docs"
Requires-Dist: sphinx_design==0.6.1; extra == "docs"
Requires-Dist: sphinx_gallery==0.17.1; extra == "docs"
Requires-Dist: matplotlib==3.9.2; extra == "docs"
Requires-Dist: numpy<2.0; extra == "docs"
Requires-Dist: pandas>=1.5.0; extra == "docs"
Requires-Dist: pandas-stubs>=1.5.0; extra == "docs"
Provides-Extra: dev
Requires-Dist: ruff>=0.7.0; extra == "dev"
Requires-Dist: pre-commit>=3.8.0; extra == "dev"
Requires-Dist: tox>=4.14.1; extra == "dev"
Requires-Dist: docplex-extensions[tests]; extra == "dev"
Requires-Dist: docplex-extensions[docs]; extra == "dev"
Dynamic: license-file
